pyredlight/__init__.py
pyredlight/fastapi.py
pyredlight/limits.py
pyredlight/redis.py
pyredlight-0.4.0.dist-info/LICENSE.md
pyredlight-0.4.0.dist-info/METADATA
pyredlight-0.4.0.dist-info/WHEEL
pyredlight-0.4.0.dist-info/RECORD
