Metadata-Version: 2.1
Name: pyredlight
Version: 0.4.0
Summary: Redis transaction based rate limiter
Home-page: https://github.com/cocreators-ee/pyredlight/
License: BSD-3-Clause
Keywords: rate,limit,limiter,limiting,async
Author: Janne Enberg
Author-email: janne.enberg@lietu.net
Requires-Python: >=3.8,<4
Classifier: License :: OSI Approved :: BSD License
Classifier: Programming Language :: Python :: 3
Classifier: Programming Language :: Python :: 3.8
Classifier: Programming Language :: Python :: 3.9
Classifier: Programming Language :: Python :: 3.10
Classifier: Programming Language :: Python :: 3.11
Classifier: Programming Language :: Python :: 3.12
Requires-Dist: redis[hiredis] (>=5.0.1,<6.0.0)
Project-URL: Documentation, https://github.com/cocreators-ee/pyredlight/
Project-URL: Repository, https://github.com/cocreators-ee/pyredlight/
